LICENSE
MANIFEST.in
README.md
setup.py
key_musicz/__init__.py
key_musicz/base.py
key_musicz/conf.py
key_musicz/fmt.py
key_musicz/help.txt
key_musicz/keyz.py
key_musicz/playz.py
key_musicz/run.py
key_musicz/soundz.py
key_musicz/sourcez.py
key_musicz.egg-info/PKG-INFO
key_musicz.egg-info/SOURCES.txt
key_musicz.egg-info/dependency_links.txt
key_musicz.egg-info/requires.txt
key_musicz.egg-info/top_level.txt
key_musicz/conf/kl.js
key_musicz/conf/kl1.js
key_musicz/conf/okl.js
key_musicz/conf/play.js
key_musicz/conf/play1.js
key_musicz/conf/play2.js
key_musicz/conf/playbb.js
key_musicz/conf/playblk.js
key_musicz/conf/playrb.js
key_musicz/conf/playrbbk.js
key_musicz/conf/test.py
key_musicz/thirdpart/pyfluidsynth/LICENSE
key_musicz/thirdpart/pyfluidsynth/fluidsynth.py