Metadata-Version: 2.1
Name: key-musicz
Version: 0.3.1
Summary: 键盘弹钢琴，keyboard to play piano
Home-page: https://github.com/buildCodeZ/key_musicz
Author: Zzz
Author-email: 1309458652@qq.com
License: Apache License 2.0
Keywords: key_musicz
Platform: any
License-File: LICENSE
